{"cameraMode":{"drawMode":0,"name":"Shaded","section":"Shading Mode"},"sceneLighting":false,"audioPlay":false,"sceneViewState":{"m_AlwaysRefresh":false,"showFog":true,"showSkybox":false,"showFlares":true,"showImageEffects":true,"showParticleSystems":true,"showVisualEffectGraphs":true,"m_FxEnabled":true},"in2DMode":false,"pivot":{"x":-10.00975513458252,"y":-3.806796073913574,"z":-4.175286769866943},"rotation":{"x":-0.007563317660242319,"y":0.8846916556358337,"z":-0.4660019874572754,"w":-0.014326129108667374},"size":6.477301597595215,"orthographic":false}